azuremarketplace/__init__.py
azuremarketplace/microsoft/__init__.py
azuremarketplace/microsoft/marketplace/__init__.py
azuremarketplace/microsoft/marketplace/meter/__init__.py
azuremarketplace/microsoft/marketplace/meter/_configuration.py
azuremarketplace/microsoft/marketplace/meter/_metering_api.py
azuremarketplace/microsoft/marketplace/meter/aio/__init__.py
azuremarketplace/microsoft/marketplace/meter/aio/_configuration.py
azuremarketplace/microsoft/marketplace/meter/aio/_metering_api.py
azuremarketplace/microsoft/marketplace/meter/aio/operations/__init__.py
azuremarketplace/microsoft/marketplace/meter/aio/operations/_metering_operations_operations.py
azuremarketplace/microsoft/marketplace/meter/models/__init__.py
azuremarketplace/microsoft/marketplace/meter/models/_metering_api_enums.py
azuremarketplace/microsoft/marketplace/meter/models/_models.py
azuremarketplace/microsoft/marketplace/meter/models/_models_py3.py
azuremarketplace/microsoft/marketplace/meter/operations/__init__.py
azuremarketplace/microsoft/marketplace/meter/operations/_metering_operations_operations.py
azuremarketplace/microsoft/marketplace/saas/__init__.py
azuremarketplace/microsoft/marketplace/saas/_configuration.py
azuremarketplace/microsoft/marketplace/saas/_saa_sapi.py
azuremarketplace/microsoft/marketplace/saas/aio/__init__.py
azuremarketplace/microsoft/marketplace/saas/aio/_configuration.py
azuremarketplace/microsoft/marketplace/saas/aio/_saa_sapi.py
azuremarketplace/microsoft/marketplace/saas/aio/operations/__init__.py
azuremarketplace/microsoft/marketplace/saas/aio/operations/_fulfillment_operations_operations.py
azuremarketplace/microsoft/marketplace/saas/aio/operations/_subscription_operations_operations.py
azuremarketplace/microsoft/marketplace/saas/models/__init__.py
azuremarketplace/microsoft/marketplace/saas/models/_models.py
azuremarketplace/microsoft/marketplace/saas/models/_models_py3.py
azuremarketplace/microsoft/marketplace/saas/models/_saa_sapi_enums.py
azuremarketplace-0.9.1.dist-info/METADATA
azuremarketplace-0.9.1.dist-info/WHEEL
azuremarketplace-0.9.1.dist-info/top_level.txt
azuremarketplace-0.9.1.dist-info/RECORD
