Metadata-Version: 2.1
Name: azuremarketplace
Version: 0.9.1
Summary: The Microsoft commercial marketplace SaaS offer billing SDK enables Partners and Startups to build the requirements for the implementation of transactable SaaS offers for both the AppSource and Azure Marketplaces.
Home-page: https://github.com/Azure/commercial-marketplace-client-python
Author: Scott Seely
Author-email: scott@scottseely.com
License: MIT
Project-URL: Source, https://github.com/Azure/commercial-marketplace-client-python
Project-URL: Tracker, https://github.com/Azure/commercial-marketplace-client-python/issues
Platform: UNKNOWN
Classifier: Development Status :: 4 - Beta
Classifier: Intended Audience :: Developers
Classifier: License :: OSI Approved :: MIT License
Classifier: Operating System :: POSIX :: Linux
Classifier: Programming Language :: Python :: 2
Classifier: Programming Language :: Python :: 2.7
Classifier: Programming Language :: Python :: 3
Classifier: Programming Language :: Python :: 3.8
Classifier: Programming Language :: Python :: 3.9
Requires-Dist: msal
Requires-Dist: azure-core
Requires-Dist: azure-identity
Requires-Dist: azure-mgmt-subscription
Requires-Dist: azure-mgmt-resource
Requires-Dist: msrest
